setup.py
sizeparse/__init__.py
sizeparse.egg-info/PKG-INFO
sizeparse.egg-info/SOURCES.txt
sizeparse.egg-info/dependency_links.txt
sizeparse.egg-info/top_level.txt