Metadata-Version: 1.1
Name: sizeparse
Version: 1.0.0
Summary: A simple Python library for parsing strings denoting byte-capacities with SI or IEC suffixes.
Home-page: https://github.com/chrisgavin/sizeparse
Author: UNKNOWN
Author-email: UNKNOWN
License: Unlicense
Platform: UNKNOWN
Classifier: License :: Public Domain
Classifier: Topic :: Software Development :: Libraries :: Python Modules
Classifier: Programming Language :: Python :: 2
Classifier: Programming Language :: Python :: 2.7
Classifier: Programming Language :: Python :: 3
Classifier: Programming Language :: Python :: 3.2
Classifier: Programming Language :: Python :: 3.3
Classifier: Programming Language :: Python :: 3.4
Classifier: Programming Language :: Python :: 3.5
Classifier: Programming Language :: Python :: 3.6
